sopel_modules.github-0.4.8-nspkg.pth
sopel_modules/github/__init__.py
sopel_modules/github/formatting.py
sopel_modules/github/github.py
sopel_modules/github/webhook.py
tests/__init__.py
tests/test_github.py
sopel_modules.github-0.4.8.dist-info/COPYING
sopel_modules.github-0.4.8.dist-info/METADATA
sopel_modules.github-0.4.8.dist-info/WHEEL
sopel_modules.github-0.4.8.dist-info/namespace_packages.txt
sopel_modules.github-0.4.8.dist-info/top_level.txt
sopel_modules.github-0.4.8.dist-info/RECORD
