Metadata-Version: 2.1
Name: sopel-modules.github
Version: 0.4.8
Summary: GitHub plugin for Sopel
Home-page: https://github.com/sopel-irc/sopel-github
Author: Max Gurela
Author-email: maxpowa@outlook.com
Maintainer: dgw
Maintainer-email: dgw@technobabbl.es
License: Eiffel Forum License, version 2
Platform: UNKNOWN
Requires-Dist: bottle (~=0.12.0)
Requires-Dist: sopel (<8,>=7.0)
